malie/__init__.py
malie-0.0.0a0.dev0.dist-info/METADATA
malie-0.0.0a0.dev0.dist-info/WHEEL
malie-0.0.0a0.dev0.dist-info/top_level.txt
malie-0.0.0a0.dev0.dist-info/RECORD
